csvcool.py
ez_setup.py
setup.py
csvcool.egg-info/PKG-INFO
csvcool.egg-info/SOURCES.txt
csvcool.egg-info/dependency_links.txt
csvcool.egg-info/top_level.txt