Metadata-Version: 1.1
Name: csvcool
Version: 0.3.5
Summary: Cool way to deal with 'headed' CSV
Home-page: http://bitbucket.org/leliel12/csvcool
Author: JBC
Author-email: jbc dot develop at gmail dot com
License: GPL3
Keywords: csv
Platform: UNKNOWN
Classifier: Development Status :: 4 - Beta
Classifier: Topic :: Utilities
Classifier: Operating System :: OS Independent
Classifier: Programming Language :: Python :: 2
